rask_njord_zzk
