Metadata-Version: 1.0
Name: rask-njord-zzk
Version: 0.0.11
Summary: Rask 00K Client
Home-page: https://gitlab.com/vikingmakt/rask_njord_zzk
Author: Umgeher Torgersen
Author-email: me@umgeher.org
License: https://gitlab.com/vikingmakt/rask_njord_zzk/raw/master/LICENSE
Platform: UNKNOWN
